proteo_estimator/__init__.py
proteo_estimator/proteo_estimator.py
proteo_estimator-1.0.5.dist-info/LICENSE
proteo_estimator-1.0.5.dist-info/METADATA
proteo_estimator-1.0.5.dist-info/WHEEL
proteo_estimator-1.0.5.dist-info/top_level.txt
proteo_estimator-1.0.5.dist-info/RECORD
