Metadata-Version: 2.1
Name: proteo-estimator
Version: 1.0.5
Summary: A package from the NCI-CPTAC DREAM Proteogenomics Challenge
Home-page: https://github.com/Sage-Bionetworks/NCI-CPTAC-DREAM-Proteogenomics-Challenge/tree/master/Subchallenges_2_3/ProteoEstimator
Author: Anna Calinawan
Author-email: anna.calinawan@mssm.edu
License: UNKNOWN
Platform: UNKNOWN
Classifier: Programming Language :: Python :: 3
Classifier: License :: CC0 1.0 Universal (CC0 1.0) Public Domain Dedication
Classifier: Operating System :: OS Independent
Requires-Dist: docker (>=4.0.1)
